CHANGES
LICENSE.txt
MANIFEST.in
README
setup.py
whoosh_igo.egg-info/PKG-INFO
whoosh_igo.egg-info/SOURCES.txt
whoosh_igo.egg-info/dependency_links.txt
whoosh_igo.egg-info/top_level.txt
whooshjp/Filters.py
whooshjp/IgoTokenizer.py
whooshjp/MeCabTokenizer.py
whooshjp/TinySegmenterTokenizer.py
whooshjp/__init__.py