Metadata-Version: 1.1
Name: whoosh-igo
Version: 0.7
Summary: tokenizers for Whoosh designed for Japanese language
Home-page: https://github.com/hideaki-t/whoosh-igo/
Author: Hideaki Takahashi
Author-email: mymelo@gmail.com
License: Apache License, Version 2.0
Keywords: japanese,tokenizer
Platform: UNKNOWN
Classifier: Development Status :: 4 - Beta
Classifier: Intended Audience :: Developers
Classifier: License :: OSI Approved :: Apache Software License
Classifier: Natural Language :: Japanese
Classifier: Operating System :: OS Independent
Classifier: Operating System :: Microsoft :: Windows
Classifier: Operating System :: POSIX :: Linux
Classifier: Programming Language :: Python :: 2.6
Classifier: Programming Language :: Python :: 2.7
Classifier: Programming Language :: Python :: 3.2
Classifier: Topic :: Scientific/Engineering :: Information Analysis
Classifier: Topic :: Software Development :: Libraries :: Python Modules
Classifier: Topic :: Text Processing :: Linguistic
